nv/utils/introspect/__init__.py
nv/utils/introspect/core.py
nv/utils/introspect/exceptions.py
nv/utils/introspect/parsers/__init__.py
nv/utils/introspect/parsers/expressions.py
nv/utils/introspect/parsers/objects.py
nv/utils/introspect/tracer.py
nv/utils/introspect/types.py
nv/utils/introspect/utils.py
nv_utils_introspect-0.2.2.dist-info/LICENSE
nv_utils_introspect-0.2.2.dist-info/WHEEL
nv_utils_introspect-0.2.2.dist-info/METADATA
nv_utils_introspect-0.2.2.dist-info/RECORD
